MANIFEST.in
README.rst
ez_setup.py
setup.cfg
setup.py
versioneer.py
okera/__init__.py
okera/_pure_sasl.py
okera/_pure_sasl_client.py
okera/_pure_sasl_mechanisms.py
okera/_thrift_api.py
okera/_thrift_util.py
okera/_util.py
okera/_version.py
okera/botocore_patch.py
okera/concurrency.py
okera/odas.py
okera/policy_sync.py
okera/utilities.py
okera/integration/__init__.py
okera/integration/domino.py
okera/integration/jupyterhub.py
okera/test_scans/__init__.py
okera/test_scans/file_format_test_common.py
okera/test_scans/test_avro.py
okera/test_scans/test_complex.py
okera/test_scans/test_hive.py
okera/test_scans/test_json.py
okera/test_scans/test_orc.py
okera/test_scans/test_parquet.py
okera/test_scans/test_scans.py
okera/test_scans/test_spark.py
okera/tests/__init__.py
okera/tests/_mr_util.py
okera/tests/create_test_data.py
okera/tests/policy_sync_util.py
okera/tests/pycerebro_test_common.py
okera/tests/snowflake_cte_test_cases.py
okera/tests/test_abac.py
okera/tests/test_access_review.py
okera/tests/test_attributes.py
okera/tests/test_attributes_unnest.py
okera/tests/test_auth.py
okera/tests/test_authorization.py
okera/tests/test_authorize_request.py
okera/tests/test_basic.py
okera/tests/test_catalog_integration.py
okera/tests/test_collibra_integration.py
okera/tests/test_configs.py
okera/tests/test_connections.py
okera/tests/test_crawler.py
okera/tests/test_cte.py
okera/tests/test_data_registration.py
okera/tests/test_deny.py
okera/tests/test_dependencies.py
okera/tests/test_fs.py
okera/tests/test_integration.py
okera/tests/test_jdbc.py
okera/tests/test_joins.py
okera/tests/test_kv_store.py
okera/tests/test_list_catalogs.py
okera/tests/test_list_databases_v2.py
okera/tests/test_list_datasets.py
okera/tests/test_mindsphere.py
okera/tests/test_misc.py
okera/tests/test_nightly.py
okera/tests/test_perf.py
okera/tests/test_policy_lifecycle.py
okera/tests/test_policy_sync.py
okera/tests/test_presto.py
okera/tests/test_privacy.py
okera/tests/test_roles.py
pyokera.egg-info/PKG-INFO
pyokera.egg-info/SOURCES.txt
pyokera.egg-info/dependency_links.txt
pyokera.egg-info/not-zip-safe
pyokera.egg-info/requires.txt
pyokera.egg-info/top_level.txt